{"$id":"9462073b-e6b4-46b3-91e0-8ef1ccd617cb","name":"The default scenario","description":"","author":"Katniss","file_version":"0.0","mod_versions":{"$type":"System.Collections.Generic.Dictionary`2[[System.String, mscorlib, Version=4.0.0.0, Culture=neutral, PublicKeyToken=b77a5c561934e089],[HSP.Content.Version, HSP.Content, Version=0.0.0.0, Culture=neutral, PublicKeyToken=null]], mscorlib, Version=4.0.0.0, Culture=neutral, PublicKeyToken=b77a5c561934e089","$id":"39787343-eb83-4367-bbe4-7afc3770d36a","value":[{"key":"Vanilla","value":"3.0"},{"key":"TestMod","value":"0.0"}]}}