{"$type":"HSP.Settings.SettingsFile, HSP.Settings, Version=0.0.0.0, Culture=neutral, PublicKeyToken=null","$id":"643a924e-016c-41e7-9a8a-7025d2d801b9","pages":{"$type":"System.Collections.Generic.List`1[[HSP.Settings.ISettingsPage, HSP.Settings, Version=0.0.0.0, Culture=neutral, PublicKeyToken=null]], mscorlib, Version=4.0.0.0, Culture=neutral, PublicKeyToken=b77a5c561934e089","$id":"38b8c3a8-e7d5-4e8e-9848-6027c063b8a4","value":[{"$type":"HSP.Vanilla.Settings.SettingsPage_Scenario, HSP.Vanilla, Version=0.0.0.0, Culture=neutral, PublicKeyToken=null","$id":"2377494c-4dce-400b-b40a-3a08655cd753"}]}}